LICENSE
MANIFEST.in
README.md
package.json
setup.py
loading_wrapper/LoadingWrapper.py
loading_wrapper/__init__.py
loading_wrapper/_imports_.py
loading_wrapper/loading_wrapper.min.js
loading_wrapper/loading_wrapper.min.js.map
loading_wrapper/metadata.json
loading_wrapper/package-info.json
loading_wrapper.egg-info/PKG-INFO
loading_wrapper.egg-info/SOURCES.txt
loading_wrapper.egg-info/dependency_links.txt
loading_wrapper.egg-info/top_level.txt