Metadata-Version: 2.1
Name: loading-wrapper
Version: 1.2.18
Summary: Dash Loading Wrapper Component
Author: s_matsumoto <s_matsumoto@thinkup-sol.co.jp>
License: MIT
Classifier: Framework :: Dash
License-File: LICENSE
